dmutils/__init__.py
dmutils/access_control.py
dmutils/asset_fingerprint.py
dmutils/authentication.py
dmutils/cloudfoundry.py
dmutils/config.py
dmutils/cookie_probe.py
dmutils/csv_generator.py
dmutils/dates.py
dmutils/deprecation.py
dmutils/direct_plus_client.py
dmutils/dmp_so_status.py
dmutils/documents.py
dmutils/env_helpers.py
dmutils/external.py
dmutils/filters.py
dmutils/flask.py
dmutils/flask_init.py
dmutils/formats.py
dmutils/jinja2_environment.py
dmutils/logging.py
dmutils/metrics.py
dmutils/ods.py
dmutils/proxy_fix.py
dmutils/py.typed
dmutils/request_id.py
dmutils/s3.py
dmutils/service_attribute.py
dmutils/session.py
dmutils/status.py
dmutils/timing.py
dmutils/urls.py
dmutils/user.py
dmutils/views.py
dmutils/email/__init__.py
dmutils/email/dm_mailchimp.py
dmutils/email/dm_notify.py
dmutils/email/exceptions.py
dmutils/email/helpers.py
dmutils/email/tokens.py
dmutils/email/user_account_email.py
dmutils/errors/__init__.py
dmutils/errors/api.py
dmutils/errors/frontend.py
dmutils/forms/__init__.py
dmutils/forms/errors.py
dmutils/forms/fields.py
dmutils/forms/filters.py
dmutils/forms/helpers.py
dmutils/forms/mixins.py
dmutils/forms/validators.py
dmutils/forms/widgets.py
dmutils/repoutils/__init__.py
digitalmarketplace_utils-60.12.0.dist-info/LICENCE
digitalmarketplace_utils-60.12.0.dist-info/METADATA
digitalmarketplace_utils-60.12.0.dist-info/WHEEL
digitalmarketplace_utils-60.12.0.dist-info/top_level.txt
digitalmarketplace_utils-60.12.0.dist-info/RECORD
