Metadata-Version: 2.1
Name: digitalmarketplace-utils
Version: 60.12.0
Summary: Common utils for Digital Marketplace apps.
Home-page: https://github.com/alphagov/digitalmarketplace-utils
Author: GDS Developers
License: MIT
Platform: UNKNOWN
Requires-Python: ~=3.8
Requires-Dist: Flask-WTF >=0.14.2
Requires-Dist: Flask <2.1,>=1.0
Requires-Dist: Flask-gzip >=0.2
Requires-Dist: Flask-Login >=0.2.11
Requires-Dist: Flask-Session >=0.3.2
Requires-Dist: boto3 <2,>=1.7.83
Requires-Dist: contextlib2 >=0.4.0
Requires-Dist: cryptography >=3.2
Requires-Dist: gds-metrics <1,>=0.2.0
Requires-Dist: govuk-country-register >=0.3.0
Requires-Dist: mailchimp3 ==3.0.17
Requires-Dist: requests <3,>=2.22.0
Requires-Dist: redis >=3.5.2
Requires-Dist: fleep <1.1,>=1.0.1
Requires-Dist: notifications-python-client <9.0.0,>=5.7.1
Requires-Dist: odfpy >=1.3.6
Requires-Dist: python-json-logger <3.0.0,>=0.1.11
Requires-Dist: pytz
Requires-Dist: unicodecsv >=0.14.1
Requires-Dist: workdays >=1.4
